setup.py
pippy/__init__.py
pippy/config.py
pippy/download.py
pippy/finder.py
pippy/install.py
pippy/req.py
pippy/runner.py
pippy/utils.py
pippy.egg-info/PKG-INFO
pippy.egg-info/SOURCES.txt
pippy.egg-info/dependency_links.txt
pippy.egg-info/entry_points.txt
pippy.egg-info/not-zip-safe
pippy.egg-info/requires.txt
pippy.egg-info/top_level.txt