Metadata-Version: 1.0
Name: pippy
Version: 0.1.0
Summary: pippy - Faster installs!
Home-page: https://github.com/ravenac95/pippy
Author: Reuven V. Gonzales
Author-email: reuven@tobetter.us
License: MIT
Platform: *nix
Classifier: License :: OSI Approved :: MIT License
Classifier: Intended Audience :: Developers
Classifier: Programming Language :: Python
Classifier: Operating System :: POSIX
Classifier: Topic :: Software Development :: Build Tools
